Workbook

Sheet staging_sales
A1: platform | B1: platform_order_id | C1: store_id | D1: order_datetime | E1: order_date | F1: order_month | G1: order_hour | H1: gross_amount | I1: commision_amount | J1: subsidy_amount | K1: net_amount
A2: shopeefood | B2: 2811601005300736156 | C2: ST_001 | D2: 45962.496 | E2: 45962 | F2: =TEXT(E2, "mmmm-yyyy") -> November-2025 | G2: 11 | H2: 21900 | I2: 4134 | J2: 5366 | K2: 12400
A3: shopeefood | B3: 2811658427779072474 | C3: ST_001 | D3: 45962.539 | E3: 45962 | F3: =TEXT(E3, "mmmm-yyyy") -> November-2025 | G3: 12 | H3: 46300 | I3: 9738 | J3: 10350 | K3: 26212
A4: shopeefood | B4: 2811780845799424389 | C4: ST_001 | D4: 45962.615 | E4: 45962 | F4: =TEXT(E4, "mmmm-yyyy") -> November-2025 | G4: 14 | H4: 18500 | I4: 3719 | J4: 3626 | K4: 11155
A5: shopeefood | B5: 2811967361435648118 | C5: ST_001 | D5: 45962.754 | E5: 45962 | F5: =TEXT(E5, "mmmm-yyyy") -> November-2025 | G5: 18 | H5: 54400 | I5: 10792 | J5: 15234 | K5: 28374
A6: shopeefood | B6: 2811989790673920250 | C6: ST_001 | D6: 45962.77 | E6: 45962 | F6: =TEXT(E6, "mmmm-yyyy") -> November-2025 | G6: 18 | H6: 48500 | I6: 10288 | J6: 10350 | K6: 27862
A7: shopeefood | B7: 2812034214808576109 | C7: ST_001 | D7: 45962.799 | E7: 45962 | F7: =TEXT(E7, "mmmm-yyyy") -> November-2025 | G7: 19 | H7: 22900 | I7: 4500 | J7: 4900 | K7: 13500
A8: shopeefood | B8: 2812081837787136935 | C8: ST_001 | D8: 45962.828 | E8: 45962 | F8: =TEXT(E8, "mmmm-yyyy") -> November-2025 | G8: 19 | H8: 22900 | I8: 4500 | J8: 4900 | K8: 13500
A9: shopeefood | B9: 2812130801846272293 | C9: ST_001 | D9: 45962.864 | E9: 45962 | F9: =TEXT(E9, "mmmm-yyyy") -> November-2025 | G9: 20 | H9: 53700 | I9: 10653 | J9: 15090 | K9: 27957
A10: shopeefood | B10: 2812112993880064778 | C10: ST_001 | D10: 45962.868 | E10: 45962 | F10: =TEXT(E10, "mmmm-yyyy") -> November-2025 | G10: 20 | H10: 50800 | I10: 10078 | J10: 14491 | K10: 26231
A11: shopeefood | B11: 2812189755918336340 | C11: ST_001 | D11: 45962.91 | E11: 45962 | F11: =TEXT(E11, "mmmm-yyyy") -> November-2025 | G11: 21 | H11: 51700 | I11: 10256 | J11: 14677 | K11: 26767
A12: shopeefood | B12: 2812210614389760752 | C12: ST_001 | D12: 45962.923 | E12: 45962 | F12: =TEXT(E12, "mmmm-yyyy") -> November-2025 | G12: 22 | H12: 52300 | I12: 10375 | J12: 14800 | K12: 27125
A13: shopeefood | B13: 2813010977048576340 | C13: ST_001 | D13: 45963.491 | E13: 45963 | F13: =TEXT(E13, "mmmm-yyyy") -> November-2025 | G13: 11 | H13: 65400 | I13: 12974 | J13: 17506 | K13: 34920
... A485: shopeefood | B485: 2868729354167296565 | C485: ST_001 | D485: 46002.835 | E485: 46002 | F485: =TEXT(E485, "mmmm-yyyy") -> December-2025 | G485: 20 | H485: 27500 | I485: 5191 | J485: 6738 | K485: 15571
A486: shopeefood | B486: 2.86874e+18 | C486: ST_001 | D486: 46002.84 | E486: 46002 | F486: =TEXT(E486, "mmmm-yyyy") -> December-2025 | G486: 20 | H486: 37200 | I486: 7463 | J486: 9350 | K486: 20387
A487: shopeefood | B487: 2868745298502144253 | C487: ST_001 | D487: 46002.846 | E487: 46002 | F487: =TEXT(E487, "mmmm-yyyy") -> December-2025 | G487: 20 | H487: 133300 | I487: 25461 | J487: 39959 | K487: 67880
A488: shopeefood | B488: 2868782135992832617 | C488: ST_001 | D488: 46002.872 | E488: 46002 | F488: =TEXT(E488, "mmmm-yyyy") -> December-2025 | G488: 20 | H488: 41200 | I488: 8463 | J488: 10350 | K488: 22387
A489: shopeefood | B489: 2868808276141056974 | C489: ST_001 | D489: 46002.891 | E489: 46002 | F489: =TEXT(E489, "mmmm-yyyy") -> December-2025 | G489: 21 | H489: 26500 | I489: 5002 | J489: 6493 | K489: 15005
A490: shopeefood | B490: 2868840082760704573 | C490: ST_001 | D490: 46002.913 | E490: 46002 | F490: =TEXT(E490, "mmmm-yyyy") -> December-2025 | G490: 21 | H490: 37000 | I490: 7290 | J490: 9840 | K490: 19870
A491: shopeefood | B491: 2868883701670400201 | C491: ST_001 | D491: 46002.944 | E491: 46002 | F491: =TEXT(E491, "mmmm-yyyy") -> December-2025 | G491: 22 | H491: 22900 | I491: 4500 | J491: 4900 | K491: 13500
A492: shopeefood | B492: 2868894586479104731 | C492: ST_001 | D492: 46002.952 | E492: 46002 | F492: =TEXT(E492, "mmmm-yyyy") -> December-2025 | G492: 22 | H492: 45800 | I492: 9123 | J492: 12310 | K492: 24367
A493: shopeefood | B493: 2869629855900160058 | C493: ST_001 | D493: 46003.471 | E493: 46003 | F493: =TEXT(E493, "mmmm-yyyy") -> December-2025 | G493: 11 | H493: 22900 | I493: 4323 | J493: 5611 | K493: 12966
A494: shopeefood | B494: 2869652380967424209 | C494: ST_001 | D494: 46003.487 | E494: 46003 | F494: =TEXT(E494, "mmmm-yyyy") -> December-2025 | G494: 11 | H494: 40800 | I494: 7750 | J494: 12800 | K494: 20250
A495: shopeefood | B495: 2869664106734592063 | C495: ST_001 | D495: 46003.495 | E495: 46003 | F495: =TEXT(E495, "mmmm-yyyy") -> December-2025 | G495: 11 | H495: 36400 | I495: 6650 | J495: 11800 | K495: 17950
A496: shopeefood | B496: 2869699804423169795 | C496: ST_001 | D496: 46003.521 | E496: 46003 | F496: =TEXT(E496, "mmmm-yyyy") -> December-2025 | G496: 12 | H496: 44300 | I496: 8013 | J496: 15250 | K496: 21037
A497: shopeefood | B497: 2869784790148096479 | C497: ST_001 | D497: 46003.581 | E497: 46003 | F497: =TEXT(E497, "mmmm-yyyy") -> December-2025 | G497: 13 | H497: 25300 | I497: 5100 | J497: 4900 | K497: 15300
A498: shopeefood | B498: 2870017985651200213 | C498: ST_001 | D498: 46003.745 | E498: 46003 | F498: =TEXT(E498, "mmmm-yyyy") -> December-2025 | G498: 17 | H498: 46800 | I498: 8638 | J498: 15250 | K498: 22912
... A1089: shopeefood | B1089: 2941064173415936996 | C1089: ST_001 | D1089: 46053.934 | E1089: 46053 | F1089: =TEXT(E1089, "mmmm-yyyy") -> January-2026 | G1089: 22 | H1089: 31700 | I1089: 6372 | J1089: 8214 | K1089: 17114

Sheet pivot_monthly
A1: order_month | B1: COUNTA of platform_order_id | C1: SUM of gross_amount | D1: SUM of commision_amount | E1: SUM of subsidy_amount | F1: SUM of net_amount
A2: 45962 | B2: 362 | C2: 13760400 | D2: 2741309 | E2: 3447543 | F2: 7571548
A3: 45992 | B3: 366 | C3: 13877500 | D3: 2777432 | E3: 3407783 | F3: 7692285
A4: 46023 | B4: 360 | C4: 12333500 | D4: 2452084 | E4: 3088989 | F4: 6792427
A5: Grand Total | B5: 1088 | C5: 39971400 | D5: 7970825 | E5: 9944315 | F5: 22056260

Sheet pivot_hourly

Sheet KPI_summary
A1: key metrics | B1: value
A2: total orders: | B2: =COUNTA(staging_sales!B:B) -> 1089
A3: gross revenue: | B3: =sum(staging_sales!H:H) -> 39971400
A4: net revenue: | B4: =SUM(staging_sales!K:K) -> 22056260
A5: platform_fee_ratio: | B5: =(SUM(staging_sales!I:I)+SUM(staging_sales!J:J))/SUM(staging_sales!H:H) -> 0.44819896
A6: average_order_value: | B6: =AVERAGE(staging_sales!H:H) -> 36738.419

Sheet dashboard
B1: Shopefood Sales Performance Dashboard
B2: Nov 2025 - Jan 2026
B4: =KPI_summary!B2 -> 1089 | D4: =KPI_summary!B3 -> 39971400 | F4: =KPI_summary!B4 -> 22056260 | H4: =KPI_summary!B5 -> 0.44819896 | J4: =KPI_summary!B6 -> 36738.419
B7: Total Orders | D7: Gross Revenue | F7: Net Revenue | H7: Platform Fee Ratio% | J7: AOV

Sheet insight_notes
A1: Section | B1: Insight
A2: Overview | B2: Analysis covers shopefood transaction from Nov 2025 to Jan 2026 with a total of 1,089 orders. The objective is to understand revenue performance, platform cost structure and customer ordering behavior.
A3: Revenue Performance | B3: Total gross revenue reached Rp39,971,400 with net revenue of Rp Rp22,056,260 over the period. Monthly performance remained relatively stable, indicating consistent demand without significant growth or decline
A4: Platform Cost | B4: Platform fees accounted for approximately 44.82% of gross transaction value, showing that commissions and promotional subsidies represent a substantial portion of total revenue. This suggest margin sesitivity to promotional intensity.
A5: Customer Behavior | B5: The average order value (AOV) was around Rp36.7K per transaction, which is typical for quick-service food categories. There is potential to increase revenue per customer through bundle offerings or upselling strategies.
A6: Peak Hours | B6: Order distribution shows clear concentration during evening hours, particularly between 8PM and 10PM. Dinner time represents the primary revenue driver, while midday demand is comparatively lower.
A7: Key Takeaways | B7: • Revenue performance is stable but not yet in a grow phase. • Platform costs significantly affect net revenue. • Evening hours are the most critical sales window. • Increasing AOV presents the main opportunity for revenue improvement
A8: Recommendation | B8: • Focus promotions during peak evening hours to maximize return • Introduce bundled menu packages to increase AOV • Monitor subsidy usage to improve margin efficiency

Sheet dim_store
A1: store_id | B1: store_name
A2: ST_001 | B2: ayam kremes sambel bawang
